{
  "repo": "modem-dev/hunk",
  "tag": "v0.17.1",
  "platforms": {
    "aarch64-darwin": {
      "binary": "hunkdiff-darwin-arm64.tar.gz",
      "binaryInArchive": "hunkdiff-darwin-arm64/hunk",
      "hash": "sha256-YsFtBMXFL/RffxrVbpqpzAlQjUVmRzPhb2iQ0CM7n/k="
    },
    "x86_64-darwin": {
      "binary": "hunkdiff-darwin-x64.tar.gz",
      "binaryInArchive": "hunkdiff-darwin-x64/hunk",
      "hash": "sha256-RRPpuSw5kbJ3Ter7ufrvh9corAoOjVYOGmtbPaECGGI="
    },
    "aarch64-linux": {
      "binary": "hunkdiff-linux-arm64.tar.gz",
      "binaryInArchive": "hunkdiff-linux-arm64/hunk",
      "hash": "sha256-6VOFhjUPvL82sUbfQyktTM4S846feNVORpUJaIHSh3s="
    },
    "x86_64-linux": {
      "binary": "hunkdiff-linux-x64.tar.gz",
      "binaryInArchive": "hunkdiff-linux-x64/hunk",
      "hash": "sha256-5O0+trpL12PnG9xj8tHu2ZP1SxiXdKUHNZLHkJUEG9Y="
    }
  }
}
